{"stats":{"minecraft:killed_by":{"minecraft:creeper":1},"minecraft:custom":{"minecraft:time_since_rest":458,"minecraft:sprint_one_cm":62315,"minecraft:damage_taken":532,"minecraft:walk_one_cm":54347,"minecraft:interact_with_anvil":2,"minecraft:mob_kills":5,"minecraft:drop":14,"minecraft:damage_dealt":700,"minecraft:fly_one_cm":813569,"minecraft:open_barrel":1,"minecraft:open_chest":2,"minecraft:crouch_one_cm":2932,"minecraft:play_time":33530,"minecraft:walk_under_water_one_cm":588,"minecraft:deaths":2,"minecraft:sneak_time":2264,"minecraft:jump":372,"minecraft:leave_game":1,"minecraft:walk_on_water_one_cm":1702,"minecraft:time_since_death":438,"minecraft:total_world_time":33530,"minecraft:climb_one_cm":519,"minecraft:fall_one_cm":2210,"minecraft:inspect_dispenser":8},"minecraft:dropped":{"minecraft:shulker_spawn_egg":1,"minecraft:netherite_sword":2,"minecraft:snowball":1,"minecraft:red_banner":2,"minecraft:iron_bars":1,"minecraft:magma_cube_spawn_egg":1,"minecraft:totem_of_undying":190,"minecraft:bone":1,"minecraft:donkey_spawn_egg":1,"minecraft:item_frame":1,"minecraft:ghast_spawn_egg":1},"minecraft:picked_up":{"minecraft:ghast_tear":1,"minecraft:tripwire_hook":1,"minecraft:sand":12,"minecraft:amethyst_shard":1,"minecraft:red_banner":2,"minecraft:gunpowder":1,"minecraft:bone":1,"minecraft:rotten_flesh":2,"minecraft:totem_of_undying":126,"minecraft:snowball":14},"minecraft:killed":{"minecraft:skeleton":2,"minecraft:zombie":1,"minecraft:ghast":2},"minecraft:used":{"minecraft:glow_squid_spawn_egg":1,"minecraft:amethyst_cluster":1,"minecraft:cow_spawn_egg":13,"minecraft:netherite_sword":5,"minecraft:red_sand":6,"minecraft:iron_bars":1,"minecraft:ghast_spawn_egg":1,"minecraft:amethyst_block":1,"minecraft:crimson_fence":2,"minecraft:command_block":2,"minecraft:red_concrete":2,"minecraft:polished_andesite":1,"minecraft:string":7,"minecraft:crimson_slab":1,"minecraft:purpur_slab":6,"minecraft:pink_stained_glass_pane":5,"minecraft:barrel":1,"minecraft:stone_brick_stairs":3,"minecraft:stone_bricks":17,"minecraft:tripwire_hook":3,"minecraft:anvil":2,"minecraft:sand":46,"minecraft:cobblestone":10,"minecraft:emerald_block":2,"minecraft:light_blue_wool":4,"minecraft:chain":3,"minecraft:pink_stained_glass":16,"minecraft:pink_terracotta":16,"minecraft:gray_wool":2,"minecraft:axolotl_bucket":1,"minecraft:snowball":92},"minecraft:mined":{"minecraft:white_stained_glass":1}},"DataVersion":2730}